bamboo/__init__.py
bamboo/bamboo.py
bamboo/categorical.py
bamboo/dates.py
bamboo/dtype_validation.py
bamboo/duplicates.py
bamboo/formatting.py
bamboo/imputation.py
bamboo/outliers.py
bamboo/pipelines.py
bamboo/profiling.py
bamboo/utils.py
bamboo/validation.py
bamboochute/__init__.py
bamboochute/bamboo.py
bamboochute/categorical.py
bamboochute/dates.py
bamboochute/dtype_validation.py
bamboochute/duplicates.py
bamboochute/formatting.py
bamboochute/imputation.py
bamboochute/outliers.py
bamboochute/pipelines.py
bamboochute/profiling.py
bamboochute/utils.py
bamboochute/validation.py
bamboochute-1.2.1.1.dist-info/LICENSE
bamboochute-1.2.1.1.dist-info/METADATA
bamboochute-1.2.1.1.dist-info/WHEEL
bamboochute-1.2.1.1.dist-info/top_level.txt
bamboochute-1.2.1.1.dist-info/RECORD
