Metadata-Version: 2.1
Name: bamboochute
Version: 1.2.1.1
Summary: Data cleaning package built on top of Pandas
Home-page: https://github.com/itaymev/bamboo
Author: Itay Mevorach
Author-email: itaym@uoregon.edu
License: UNKNOWN
Platform: UNKNOWN
Classifier: Development Status :: 4 - Beta
Classifier: Intended Audience :: Developers
Classifier: License :: OSI Approved :: MIT License
Classifier: Programming Language :: Python :: 3.12
Requires-Python: >=3.6
Requires-Dist: pandas (>=1.4.0)
Requires-Dist: numpy (>=1.18.0)
Requires-Dist: scikit-learn (>=0.24.0)
Requires-Dist: fancyimpute (>=0.7.0)
